malss/__init__.py
malss/algorithm.py
malss/clustering.py
malss/data.py
malss/hierarchy.py
malss/malss.py
malss/metrics.py
malss/rfpimp.py
malss/test.py
malss/app/__init__.py
malss/app/analysis.py
malss/app/analyzer.py
malss/app/app.py
malss/app/bias_variance.py
malss/app/content.py
malss/app/data_check.py
malss/app/error.py
malss/app/feature_selection.py
malss/app/introduction.py
malss/app/learning_curve.py
malss/app/learning_curve_base.py
malss/app/menuview.py
malss/app/nonscroll_table.py
malss/app/overfitting.py
malss/app/params.py
malss/app/prediction.py
malss/app/results.py
malss/app/results_base.py
malss/app/rfpimp.py
malss/app/set_file.py
malss/app/type_of_task.py
malss/app/waiting_animation.py
malss/app/static/bias_variance_en.png
malss/app/static/bias_variance_en.txt
malss/app/static/bias_variance_jp.png
malss/app/static/bias_variance_jp.txt
malss/app/static/categorical_en.txt
malss/app/static/categorical_jp.txt
malss/app/static/check_curve_en.txt
malss/app/static/check_curve_jp.txt
malss/app/static/cross_validation_en.png
malss/app/static/cross_validation_en.txt
malss/app/static/cross_validation_jp.png
malss/app/static/cross_validation_jp.txt
malss/app/static/dummy_en.png
malss/app/static/dummy_en.txt
malss/app/static/dummy_jp.png
malss/app/static/dummy_jp.txt
malss/app/static/format_en.png
malss/app/static/format_en.txt
malss/app/static/format_jp.png
malss/app/static/format_jp.txt
malss/app/static/hyperparameter_en.png
malss/app/static/hyperparameter_en.txt
malss/app/static/hyperparameter_jp.png
malss/app/static/hyperparameter_jp.txt
malss/app/static/introduction_en.txt
malss/app/static/introduction_jp.txt
malss/app/static/learning_curve_2_en.txt
malss/app/static/learning_curve_2_jp.txt
malss/app/static/learning_curve_en.png
malss/app/static/learning_curve_en.txt
malss/app/static/learning_curve_jp.png
malss/app/static/learning_curve_jp.txt
malss/app/static/overfitting_en.png
malss/app/static/overfitting_en.txt
malss/app/static/overfitting_jp.png
malss-2.4.2.dist-info/LICENSE.txt
malss-2.4.2.dist-info/METADATA
malss-2.4.2.dist-info/WHEEL
malss-2.4.2.dist-info/top_level.txt
malss-2.4.2.dist-info/RECORD
