Metadata-Version: 2.1
Name: malss
Version: 2.4.2
Summary: MALSS: MAchine Learning Support System
Home-page: https://github.com/canard0328/malss/
Author: Ryota KAMOSHIDA
Author-email: malss@malss.com
License: MIT License: http://www.opensource.org/licenses/mit-license.php
Keywords: machine learning support system
Platform: UNKNOWN
Classifier: Development Status :: 4 - Beta
Classifier: Environment :: Console
Classifier: Intended Audience :: Developers
Classifier: License :: OSI Approved :: MIT License
Classifier: Operating System :: OS Independent
Classifier: Programming Language :: Python
Classifier: Topic :: Scientific/Engineering :: Artificial Intelligence
Requires-Python: >=3.9
License-File: LICENSE.txt
Requires-Dist: scikit-learn (>=1.1.1)
Requires-Dist: matplotlib (>=3.4.3)
Requires-Dist: pandas (>=1.3.3)
Requires-Dist: jinja2 (>=3.1.2)
